django_otp_rest_auth-0.2.4.dist-info/licenses/LICENSE
otp_rest_auth/__init__.py
otp_rest_auth/adapter.py
otp_rest_auth/admin.py
otp_rest_auth/app_settings.py
otp_rest_auth/apps.py
otp_rest_auth/auth_backends.py
otp_rest_auth/jwt_auth.py
otp_rest_auth/models.py
otp_rest_auth/otp_ops.py
otp_rest_auth/serializers.py
otp_rest_auth/signals.py
otp_rest_auth/urls.py
otp_rest_auth/utils.py
otp_rest_auth/views.py
otp_rest_auth/__pycache__/__init__.cpython-310.pyc
otp_rest_auth/__pycache__/__init__.cpython-312.pyc
otp_rest_auth/__pycache__/adapter.cpython-312.pyc
otp_rest_auth/__pycache__/admin.cpython-312.pyc
otp_rest_auth/__pycache__/app_settings.cpython-312.pyc
otp_rest_auth/__pycache__/apps.cpython-312.pyc
otp_rest_auth/__pycache__/auth_backends.cpython-312.pyc
otp_rest_auth/__pycache__/jwt_auth.cpython-312.pyc
otp_rest_auth/__pycache__/models.cpython-312.pyc
otp_rest_auth/__pycache__/otp_ops.cpython-312.pyc
otp_rest_auth/__pycache__/serializers.cpython-312.pyc
otp_rest_auth/__pycache__/signals.cpython-312.pyc
otp_rest_auth/__pycache__/urls.cpython-312.pyc
otp_rest_auth/__pycache__/utils.cpython-312.pyc
otp_rest_auth/__pycache__/views.cpython-312.pyc
otp_rest_auth/migrations/0001_initial.py
otp_rest_auth/migrations/0002_totpmetadata.py
otp_rest_auth/migrations/__init__.py
otp_rest_auth/migrations/__pycache__/0001_initial.cpython-312.pyc
otp_rest_auth/migrations/__pycache__/0002_totpmetadata.cpython-312.pyc
otp_rest_auth/migrations/__pycache__/__init__.cpython-312.pyc
otp_rest_auth/templates/account/email/base_subject.txt
otp_rest_auth/templates/account/email/end_message.txt
otp_rest_auth/templates/account/email/otp_account_confirmation_message.txt
otp_rest_auth/templates/account/email/otp_account_confirmation_subject.txt
otp_rest_auth/templates/account/email/otp_email_confirmation_message.txt
otp_rest_auth/templates/account/email/otp_email_confirmation_subject.txt
otp_rest_auth/templates/account/email/otp_password_reset_message.txt
otp_rest_auth/templates/account/email/otp_password_reset_subject.txt
django_otp_rest_auth-0.2.4.dist-info/METADATA
django_otp_rest_auth-0.2.4.dist-info/WHEEL
django_otp_rest_auth-0.2.4.dist-info/top_level.txt
django_otp_rest_auth-0.2.4.dist-info/RECORD
