Metadata-Version: 2.4
Name: django-otp-rest-auth
Version: 0.2.4
Summary: Authentication and Registration in Django Rest Framework.
Home-page: https://github.com/Leptons-Multiconcept/django-otp-rest-auth
Author: Leptons Multiconcept
Author-email: dmccleptons@gmail.com
License: MIT
Classifier: Development Status :: 4 - Beta
Classifier: Topic :: Internet :: WWW/HTTP
Classifier: Framework :: Django
Classifier: Framework :: Django :: 4.2
Classifier: Framework :: Django :: 5.0
Classifier: Environment :: Web Environment
Classifier: Intended Audience :: Developers
Classifier: License :: OSI Approved :: MIT License
Classifier: Operating System :: OS Independent
Classifier: Programming Language :: Python
Classifier: Programming Language :: Python :: 3
Classifier: Programming Language :: Python :: 3.8
Classifier: Programming Language :: Python :: 3.9
Classifier: Programming Language :: Python :: 3.10
Classifier: Programming Language :: Python :: 3.11
Classifier: Programming Language :: Python :: 3.12
Requires-Python: >=3.8
License-File: LICENSE
Requires-Dist: Django>=4.2
Requires-Dist: twilio>=9.2.2
Requires-Dist: phonenumbers>=8.13.39
Requires-Dist: djangorestframework>=3.13.0
Requires-Dist: django-phonenumber-field>=7.3.0
Requires-Dist: djangorestframework-simplejwt>=5.3.1
Provides-Extra: dev
Requires-Dist: pytest; extra == "dev"
Requires-Dist: pytest-django; extra == "dev"
Dynamic: license-file
